altwer/__init__.py
altwer/altwer.py
altwer-0.4.0.dist-info/licenses/LICENSE
altwer-0.4.0.dist-info/METADATA
altwer-0.4.0.dist-info/WHEEL
altwer-0.4.0.dist-info/top_level.txt
altwer-0.4.0.dist-info/RECORD
