Metadata-Version: 2.4
Name: altwer
Version: 0.4.0
Summary: Evaluate ASR output while accounting for orthographic variation.
Home-page: https://github.com/peregilk/altwer
Author: Per Kummervold
Author-email: Per Kummervold <Per.Kummervold@nb.no>
Project-URL: Homepage, https://github.com/peregilk/altwer
Project-URL: Repository, https://github.com/peregilk/altwer
Classifier: Programming Language :: Python :: 3
Classifier: License :: OSI Approved :: MIT License
Classifier: Operating System :: OS Independent
Requires-Python: >=3.7
License-File: LICENSE
Requires-Dist: jiwer>=2.0.0
Dynamic: author
Dynamic: home-page
Dynamic: license-file
Dynamic: requires-python
